{
  "date": "2026-07-21",
  "generated_at": "2026-07-21T22:27:30.187Z",
  "source_of_truth": "LyDia Pitcher Matchup Tool",
  "source_version": "pitcher-matchup-core-v1",
  "method": "Season pitching stats plus starter-only game logs for mixed-role pitchers. The Pitcher Matchup Tool and matchup pages read this same source.",
  "pitchers_by_id": {
    "547179": {
      "id": 547179,
      "name": "Michael Lorenzen",
      "hand": "R",
      "era": 6.22,
      "whip": 1.77,
      "ip": 97,
      "so": 73,
      "bb": 38,
      "hr": 14,
      "gs": 20,
      "gp": 21,
      "w": 3,
      "l": 9,
      "bf": 463,
      "go": 111,
      "ao": 102,
      "h": 134,
      "ab": 413,
      "sf": 6,
      "starterIp": 95.99999999999999,
      "starterGames": 20
    },
    "554430": {
      "id": 554430,
      "name": "Zack Wheeler",
      "hand": "R",
      "era": 2.13,
      "whip": 0.89,
      "ip": 93,
      "so": 108,
      "bb": 22,
      "hr": 10,
      "gs": 15,
      "gp": 15,
      "w": 10,
      "l": 1,
      "bf": 355,
      "go": 83,
      "ao": 79,
      "h": 61,
      "ab": 330,
      "sf": 1,
      "starterIp": 93,
      "starterGames": 15
    },
    "592332": {
      "id": 592332,
      "name": "Kevin Gausman",
      "hand": "R",
      "era": 4.33,
      "whip": 1.22,
      "ip": 112.33333333333333,
      "so": 116,
      "bb": 32,
      "hr": 15,
      "gs": 20,
      "gp": 20,
      "w": 4,
      "l": 8,
      "bf": 470,
      "go": 97,
      "ao": 119,
      "h": 105,
      "ab": 430,
      "sf": 3,
      "starterIp": 112.33333333333333,
      "starterGames": 20
    },
    "621111": {
      "id": 621111,
      "name": "Walker Buehler",
      "hand": "R",
      "era": 5.36,
      "whip": 1.44,
      "ip": 89,
      "so": 81,
      "bb": 35,
      "hr": 12,
      "gs": 19,
      "gp": 19,
      "w": 5,
      "l": 5,
      "bf": 388,
      "go": 91,
      "ao": 84,
      "h": 93,
      "ab": 349,
      "sf": 0,
      "starterIp": 89,
      "starterGames": 19
    },
    "622491": {
      "id": 622491,
      "name": "Luis Castillo",
      "hand": "R",
      "era": 4.93,
      "whip": 1.37,
      "ip": 87.66666666666667,
      "so": 81,
      "bb": 28,
      "hr": 12,
      "gs": 15,
      "gp": 18,
      "w": 3,
      "l": 8,
      "bf": 390,
      "go": 82,
      "ao": 101,
      "h": 92,
      "ab": 349,
      "sf": 3,
      "starterIp": 76.33333333333331,
      "starterGames": 15
    },
    "625643": {
      "id": 625643,
      "name": "Reynaldo López",
      "hand": "R",
      "era": 3.5,
      "whip": 1.26,
      "ip": 61.666666666666664,
      "so": 54,
      "bb": 25,
      "hr": 8,
      "gs": 9,
      "gp": 22,
      "w": 4,
      "l": 2,
      "bf": 260,
      "go": 57,
      "ao": 69,
      "h": 53,
      "ab": 232,
      "sf": 1,
      "starterIp": 39.66666666666667,
      "starterGames": 9
    },
    "641816": {
      "id": 641816,
      "name": "Tyler Mahle",
      "hand": "R",
      "era": 5.31,
      "whip": 1.46,
      "ip": 78,
      "so": 73,
      "bb": 32,
      "hr": 12,
      "gs": 15,
      "gp": 15,
      "w": 2,
      "l": 8,
      "bf": 337,
      "go": 75,
      "ao": 75,
      "h": 82,
      "ab": 299,
      "sf": 4,
      "starterIp": 78,
      "starterGames": 15
    },
    "656849": {
      "id": 656849,
      "name": "David Peterson",
      "hand": "L",
      "era": 6.45,
      "whip": 1.64,
      "ip": 82.33333333333333,
      "so": 70,
      "bb": 37,
      "hr": 9,
      "gs": 11,
      "gp": 19,
      "w": 4,
      "l": 7,
      "bf": 382,
      "go": 99,
      "ao": 75,
      "h": 98,
      "ab": 336,
      "sf": 5,
      "starterIp": 51.66666666666666,
      "starterGames": 11
    },
    "656876": {
      "id": 656876,
      "name": "Drew Rasmussen",
      "hand": "R",
      "era": 3.26,
      "whip": 0.95,
      "ip": 99.33333333333333,
      "so": 98,
      "bb": 17,
      "hr": 12,
      "gs": 18,
      "gp": 18,
      "w": 7,
      "l": 5,
      "bf": 392,
      "go": 106,
      "ao": 89,
      "h": 77,
      "ab": 369,
      "sf": 1,
      "starterIp": 99.33333333333333,
      "starterGames": 18
    },
    "663969": {
      "id": 663969,
      "name": "Tyler Phillips",
      "hand": "R",
      "era": 3.48,
      "whip": 1.39,
      "ip": 75,
      "so": 56,
      "bb": 35,
      "hr": 8,
      "gs": 9,
      "gp": 25,
      "w": 2,
      "l": 4,
      "bf": 324,
      "go": 88,
      "ao": 73,
      "h": 69,
      "ab": 285,
      "sf": 0,
      "starterIp": 40.33333333333333,
      "starterGames": 9
    },
    "664285": {
      "id": 664285,
      "name": "Framber Valdez",
      "hand": "L",
      "era": 4.1,
      "whip": 1.32,
      "ip": 107.66666666666667,
      "so": 87,
      "bb": 36,
      "hr": 11,
      "gs": 19,
      "gp": 19,
      "w": 5,
      "l": 6,
      "bf": 469,
      "go": 131,
      "ao": 99,
      "h": 106,
      "ab": 420,
      "sf": 3,
      "starterIp": 107.66666666666667,
      "starterGames": 19
    },
    "669461": {
      "id": 669461,
      "name": "Matthew Liberatore",
      "hand": "L",
      "era": 5,
      "whip": 1.48,
      "ip": 93.66666666666667,
      "so": 88,
      "bb": 36,
      "hr": 17,
      "gs": 19,
      "gp": 19,
      "w": 5,
      "l": 6,
      "bf": 412,
      "go": 70,
      "ao": 111,
      "h": 103,
      "ab": 365,
      "sf": 6,
      "starterIp": 93.66666666666667,
      "starterGames": 19
    },
    "677958": {
      "id": 677958,
      "name": "Kumar Rocker",
      "hand": "R",
      "era": 4.4,
      "whip": 1.37,
      "ip": 90,
      "so": 80,
      "bb": 34,
      "hr": 12,
      "gs": 16,
      "gp": 18,
      "w": 2,
      "l": 8,
      "bf": 390,
      "go": 92,
      "ao": 92,
      "h": 89,
      "ab": 350,
      "sf": 3,
      "starterIp": 77.33333333333334,
      "starterGames": 16
    },
    "678022": {
      "id": 678022,
      "name": "Jack Perkins",
      "hand": "R",
      "era": 6.87,
      "whip": 1.44,
      "ip": 57.666666666666664,
      "so": 72,
      "bb": 23,
      "hr": 10,
      "gs": 6,
      "gp": 24,
      "w": 2,
      "l": 5,
      "bf": 264,
      "go": 40,
      "ao": 62,
      "h": 60,
      "ab": 231,
      "sf": 3,
      "starterIp": 26.666666666666668,
      "starterGames": 6
    },
    "679883": {
      "id": 679883,
      "name": "Luinder Avila",
      "hand": "R",
      "era": 5.08,
      "whip": 1.62,
      "ip": 56.666666666666664,
      "so": 50,
      "bb": 34,
      "hr": 6,
      "gs": 9,
      "gp": 18,
      "w": 4,
      "l": 3,
      "bf": 248,
      "go": 59,
      "ao": 46,
      "h": 58,
      "ab": 210,
      "sf": 2,
      "starterIp": 38.33333333333333,
      "starterGames": 9
    },
    "680694": {
      "id": 680694,
      "name": "Kyle Bradish",
      "hand": "R",
      "era": 3.61,
      "whip": 1.35,
      "ip": 107.33333333333333,
      "so": 106,
      "bb": 50,
      "hr": 12,
      "gs": 19,
      "gp": 19,
      "w": 6,
      "l": 9,
      "bf": 454,
      "go": 118,
      "ao": 84,
      "h": 95,
      "ab": 401,
      "sf": 2,
      "starterIp": 107.33333333333333,
      "starterGames": 19
    },
    "680736": {
      "id": 680736,
      "name": "Justin Wrobleski",
      "hand": "L",
      "era": 2.69,
      "whip": 1.02,
      "ip": 100.33333333333333,
      "so": 73,
      "bb": 20,
      "hr": 8,
      "gs": 15,
      "gp": 16,
      "w": 10,
      "l": 2,
      "bf": 399,
      "go": 92,
      "ao": 129,
      "h": 82,
      "ab": 375,
      "sf": 1,
      "starterIp": 96.33333333333333,
      "starterGames": 15
    },
    "684442": {
      "id": 684442,
      "name": "Kohl Drake",
      "hand": "L",
      "era": null,
      "whip": null,
      "ip": 0,
      "so": 0,
      "bb": 0,
      "hr": 0,
      "gs": 0,
      "gp": null,
      "w": 0,
      "l": 0,
      "bf": 0,
      "go": 0,
      "ao": 0,
      "h": 0,
      "ab": 0,
      "sf": 0,
      "starterIp": null,
      "starterGames": null
    },
    "687075": {
      "id": 687075,
      "name": "Brandon Sproat",
      "hand": "R",
      "era": 5.16,
      "whip": 1.37,
      "ip": 82,
      "so": 87,
      "bb": 39,
      "hr": 15,
      "gs": 16,
      "gp": 18,
      "w": 3,
      "l": 4,
      "bf": 352,
      "go": 71,
      "ao": 73,
      "h": 73,
      "ab": 302,
      "sf": 0,
      "starterIp": 74.66666666666666,
      "starterGames": 16
    },
    "687223": {
      "id": 687223,
      "name": "Carson Palmquist",
      "hand": "L",
      "era": 6.52,
      "whip": 1.45,
      "ip": 9.666666666666666,
      "so": 12,
      "bb": 2,
      "hr": 1,
      "gs": 3,
      "gp": 6,
      "w": 0,
      "l": 1,
      "bf": 43,
      "go": 5,
      "ao": 10,
      "h": 12,
      "ab": 39,
      "sf": 0,
      "starterIp": 7.333333333333334,
      "starterGames": 3
    },
    "695505": {
      "id": 695505,
      "name": "Chase Burns",
      "hand": "R",
      "era": 2.54,
      "whip": 1.11,
      "ip": 102.66666666666667,
      "so": 118,
      "bb": 37,
      "hr": 12,
      "gs": 18,
      "gp": 18,
      "w": 11,
      "l": 1,
      "bf": 413,
      "go": 72,
      "ao": 108,
      "h": 77,
      "ab": 374,
      "sf": 1,
      "starterIp": 102.66666666666667,
      "starterGames": 18
    },
    "696070": {
      "id": 696070,
      "name": "Kendry Rojas",
      "hand": "L",
      "era": 2.79,
      "whip": 1.6,
      "ip": 19.333333333333332,
      "so": 22,
      "bb": 16,
      "hr": 1,
      "gs": 2,
      "gp": 8,
      "w": 1,
      "l": 1,
      "bf": 86,
      "go": 14,
      "ao": 18,
      "h": 15,
      "ab": 68,
      "sf": 0,
      "starterIp": 6,
      "starterGames": 2
    },
    "696149": {
      "id": 696149,
      "name": "Bubba Chandler",
      "hand": "R",
      "era": 4.77,
      "whip": 1.45,
      "ip": 94.33333333333333,
      "so": 85,
      "bb": 55,
      "hr": 10,
      "gs": 18,
      "gp": 19,
      "w": 3,
      "l": 8,
      "bf": 421,
      "go": 78,
      "ao": 115,
      "h": 82,
      "ab": 357,
      "sf": 2,
      "starterIp": 88.99999999999999,
      "starterGames": 18
    },
    "700712": {
      "id": 700712,
      "name": "Walbert Ureña",
      "hand": "R",
      "era": 2.88,
      "whip": 1.32,
      "ip": 81.33333333333333,
      "so": 78,
      "bb": 46,
      "hr": 5,
      "gs": 15,
      "gp": 17,
      "w": 5,
      "l": 7,
      "bf": 354,
      "go": 93,
      "ao": 69,
      "h": 61,
      "ab": 299,
      "sf": 2,
      "starterIp": 79.66666666666666,
      "starterGames": 15
    },
    "700842": {
      "id": 700842,
      "name": "Eduardo Rivera",
      "hand": "L",
      "era": 2.89,
      "whip": 0.96,
      "ip": 9.333333333333334,
      "so": 9,
      "bb": 4,
      "hr": 1,
      "gs": 2,
      "gp": 3,
      "w": 0,
      "l": 0,
      "bf": 36,
      "go": 10,
      "ao": 8,
      "h": 5,
      "ab": 32,
      "sf": 0,
      "starterIp": 6,
      "starterGames": 2
    },
    "701542": {
      "id": 701542,
      "name": "Will Warren",
      "hand": "R",
      "era": 4.03,
      "whip": 1.36,
      "ip": 98.33333333333333,
      "so": 96,
      "bb": 33,
      "hr": 14,
      "gs": 19,
      "gp": 19,
      "w": 7,
      "l": 4,
      "bf": 429,
      "go": 97,
      "ao": 97,
      "h": 101,
      "ab": 385,
      "sf": 5,
      "starterIp": 98.33333333333333,
      "starterGames": 19
    },
    "702273": {
      "id": 702273,
      "name": "Noah Schultz",
      "hand": "L",
      "era": 5.6,
      "whip": 1.36,
      "ip": 53,
      "so": 47,
      "bb": 29,
      "hr": 8,
      "gs": 11,
      "gp": 11,
      "w": 3,
      "l": 6,
      "bf": 231,
      "go": 47,
      "ao": 59,
      "h": 43,
      "ab": 192,
      "sf": 1,
      "starterIp": 53,
      "starterGames": 11
    },
    "800048": {
      "id": 800048,
      "name": "Parker Messick",
      "hand": "L",
      "era": 2.73,
      "whip": 1.07,
      "ip": 112,
      "so": 110,
      "bb": 36,
      "hr": 10,
      "gs": 19,
      "gp": 19,
      "w": 8,
      "l": 5,
      "bf": 445,
      "go": 106,
      "ao": 108,
      "h": 84,
      "ab": 402,
      "sf": 3,
      "starterIp": 112,
      "starterGames": 19
    },
    "804267": {
      "id": 804267,
      "name": "Zac Thornton",
      "hand": "L",
      "era": 2.6,
      "whip": 0.92,
      "ip": 17.333333333333332,
      "so": 15,
      "bb": 5,
      "hr": 1,
      "gs": 3,
      "gp": 3,
      "w": 0,
      "l": 1,
      "bf": 67,
      "go": 17,
      "ao": 19,
      "h": 11,
      "ab": 61,
      "sf": 0,
      "starterIp": 17.333333333333332,
      "starterGames": 3
    },
    "837227": {
      "id": 837227,
      "name": "Tatsuya Imai",
      "hand": "R",
      "era": 6.06,
      "whip": 1.5,
      "ip": 52,
      "so": 63,
      "bb": 33,
      "hr": 9,
      "gs": 13,
      "gp": 13,
      "w": 5,
      "l": 4,
      "bf": 233,
      "go": 46,
      "ao": 42,
      "h": 45,
      "ab": 194,
      "sf": 1,
      "starterIp": 52,
      "starterGames": 13
    }
  },
  "games": {
    "822787": {
      "game_pk": 822787,
      "game": "Tampa Bay Rays @ Toronto Blue Jays",
      "away_team": "Tampa Bay Rays",
      "home_team": "Toronto Blue Jays",
      "away": {
        "id": 656876,
        "name": "Drew Rasmussen",
        "hand": "R",
        "era": 3.26,
        "whip": 0.95,
        "ip": 99.33333333333333,
        "so": 98,
        "bb": 17,
        "hr": 12,
        "gs": 18,
        "gp": 18,
        "w": 7,
        "l": 5,
        "bf": 392,
        "go": 106,
        "ao": 89,
        "h": 77,
        "ab": 369,
        "sf": 1,
        "starterIp": 99.33333333333333,
        "starterGames": 18,
        "score": 78,
        "grade": "Strong",
        "note": null,
        "k9": 8.879194630872483,
        "bb9": 1.5402684563758389,
        "kbbPct": 0.2066326530612245,
        "gbPct": 0.5435897435897435,
        "babip": 0.25,
        "hr9": 1.087248322147651,
        "ipStart": 5.518518518518518
      },
      "home": {
        "id": 592332,
        "name": "Kevin Gausman",
        "hand": "R",
        "era": 4.33,
        "whip": 1.22,
        "ip": 112.33333333333333,
        "so": 116,
        "bb": 32,
        "hr": 15,
        "gs": 20,
        "gp": 20,
        "w": 4,
        "l": 8,
        "bf": 470,
        "go": 97,
        "ao": 119,
        "h": 105,
        "ab": 430,
        "sf": 3,
        "starterIp": 112.33333333333333,
        "starterGames": 20,
        "score": 65,
        "grade": "Above avg",
        "note": null,
        "k9": 9.293768545994066,
        "bb9": 2.56379821958457,
        "kbbPct": 0.17872340425531916,
        "gbPct": 0.44907407407407407,
        "babip": 0.2980132450331126,
        "hr9": 1.2017804154302671,
        "ipStart": 5.616666666666666
      },
      "gap": 13,
      "strength": "Moderate",
      "edge_team": "Tampa Bay Rays"
    },
    "822871": {
      "game_pk": 822871,
      "game": "Chicago White Sox @ Texas Rangers",
      "away_team": "Chicago White Sox",
      "home_team": "Texas Rangers",
      "away": {
        "id": 702273,
        "name": "Noah Schultz",
        "hand": "L",
        "era": 5.6,
        "whip": 1.36,
        "ip": 53,
        "so": 47,
        "bb": 29,
        "hr": 8,
        "gs": 11,
        "gp": 11,
        "w": 3,
        "l": 6,
        "bf": 231,
        "go": 47,
        "ao": 59,
        "h": 43,
        "ab": 192,
        "sf": 1,
        "starterIp": 53,
        "starterGames": 11,
        "score": 47,
        "grade": "Below avg",
        "note": null,
        "k9": 7.981132075471699,
        "bb9": 4.9245283018867925,
        "kbbPct": 0.07792207792207792,
        "gbPct": 0.44339622641509435,
        "babip": 0.2536231884057971,
        "hr9": 1.3584905660377358,
        "ipStart": 4.818181818181818
      },
      "home": {
        "id": 677958,
        "name": "Kumar Rocker",
        "hand": "R",
        "era": 4.4,
        "whip": 1.37,
        "ip": 90,
        "so": 80,
        "bb": 34,
        "hr": 12,
        "gs": 16,
        "gp": 18,
        "w": 2,
        "l": 8,
        "bf": 390,
        "go": 92,
        "ao": 92,
        "h": 89,
        "ab": 350,
        "sf": 3,
        "starterIp": 77.33333333333334,
        "starterGames": 16,
        "score": 59,
        "grade": "Average",
        "note": null,
        "k9": 8,
        "bb9": 3.4,
        "kbbPct": 0.11794871794871795,
        "gbPct": 0.5,
        "babip": 0.2950191570881226,
        "hr9": 1.2,
        "ipStart": 4.833333333333334
      },
      "gap": 12,
      "strength": "Moderate",
      "edge_team": "Texas Rangers"
    },
    "823114": {
      "game_pk": 823114,
      "game": "Cincinnati Reds @ Seattle Mariners",
      "away_team": "Cincinnati Reds",
      "home_team": "Seattle Mariners",
      "away": {
        "id": 695505,
        "name": "Chase Burns",
        "hand": "R",
        "era": 2.54,
        "whip": 1.11,
        "ip": 102.66666666666667,
        "so": 118,
        "bb": 37,
        "hr": 12,
        "gs": 18,
        "gp": 18,
        "w": 11,
        "l": 1,
        "bf": 413,
        "go": 72,
        "ao": 108,
        "h": 77,
        "ab": 374,
        "sf": 1,
        "starterIp": 102.66666666666667,
        "starterGames": 18,
        "score": 79,
        "grade": "Strong",
        "note": null,
        "k9": 10.344155844155845,
        "bb9": 3.2435064935064934,
        "kbbPct": 0.19612590799031476,
        "gbPct": 0.4,
        "babip": 0.2653061224489796,
        "hr9": 1.051948051948052,
        "ipStart": 5.703703703703704
      },
      "home": {
        "id": 622491,
        "name": "Luis Castillo",
        "hand": "R",
        "era": 4.93,
        "whip": 1.37,
        "ip": 87.66666666666667,
        "so": 81,
        "bb": 28,
        "hr": 12,
        "gs": 15,
        "gp": 18,
        "w": 3,
        "l": 8,
        "bf": 390,
        "go": 82,
        "ao": 101,
        "h": 92,
        "ab": 349,
        "sf": 3,
        "starterIp": 76.33333333333331,
        "starterGames": 15,
        "score": 56,
        "grade": "Average",
        "note": null,
        "k9": 8.315589353612166,
        "bb9": 2.8745247148288975,
        "kbbPct": 0.1358974358974359,
        "gbPct": 0.44808743169398907,
        "babip": 0.3088803088803089,
        "hr9": 1.231939163498099,
        "ipStart": 5.088888888888888
      },
      "gap": 23,
      "strength": "Strong",
      "edge_team": "Cincinnati Reds"
    },
    "823437": {
      "game_pk": 823437,
      "game": "Los Angeles Dodgers @ Philadelphia Phillies",
      "away_team": "Los Angeles Dodgers",
      "home_team": "Philadelphia Phillies",
      "away": {
        "id": 680736,
        "name": "Justin Wrobleski",
        "hand": "L",
        "era": 2.69,
        "whip": 1.02,
        "ip": 100.33333333333333,
        "so": 73,
        "bb": 20,
        "hr": 8,
        "gs": 15,
        "gp": 16,
        "w": 10,
        "l": 2,
        "bf": 399,
        "go": 92,
        "ao": 129,
        "h": 82,
        "ab": 375,
        "sf": 1,
        "starterIp": 96.33333333333333,
        "starterGames": 15,
        "score": 79,
        "grade": "Strong",
        "note": null,
        "k9": 6.548172757475083,
        "bb9": 1.7940199335548173,
        "kbbPct": 0.13283208020050125,
        "gbPct": 0.416289592760181,
        "babip": 0.25084745762711863,
        "hr9": 0.717607973421927,
        "ipStart": 6.422222222222222
      },
      "home": {
        "id": 554430,
        "name": "Zack Wheeler",
        "hand": "R",
        "era": 2.13,
        "whip": 0.89,
        "ip": 93,
        "so": 108,
        "bb": 22,
        "hr": 10,
        "gs": 15,
        "gp": 15,
        "w": 10,
        "l": 1,
        "bf": 355,
        "go": 83,
        "ao": 79,
        "h": 61,
        "ab": 330,
        "sf": 1,
        "starterIp": 93,
        "starterGames": 15,
        "score": 83,
        "grade": "Strong",
        "note": null,
        "k9": 10.451612903225808,
        "bb9": 2.129032258064516,
        "kbbPct": 0.24225352112676057,
        "gbPct": 0.5123456790123457,
        "babip": 0.23943661971830985,
        "hr9": 0.967741935483871,
        "ipStart": 6.2
      },
      "gap": 4,
      "strength": "Slight",
      "edge_team": "Philadelphia Phillies"
    },
    "823519": {
      "game_pk": 823519,
      "game": "Pittsburgh Pirates @ New York Yankees",
      "away_team": "Pittsburgh Pirates",
      "home_team": "New York Yankees",
      "away": {
        "id": 696149,
        "name": "Bubba Chandler",
        "hand": "R",
        "era": 4.77,
        "whip": 1.45,
        "ip": 94.33333333333333,
        "so": 85,
        "bb": 55,
        "hr": 10,
        "gs": 18,
        "gp": 19,
        "w": 3,
        "l": 8,
        "bf": 421,
        "go": 78,
        "ao": 115,
        "h": 82,
        "ab": 357,
        "sf": 2,
        "starterIp": 88.99999999999999,
        "starterGames": 18,
        "score": 52,
        "grade": "Below avg",
        "note": null,
        "k9": 8.109540636042404,
        "bb9": 5.247349823321555,
        "kbbPct": 0.07125890736342043,
        "gbPct": 0.40414507772020725,
        "babip": 0.2727272727272727,
        "hr9": 0.9540636042402827,
        "ipStart": 4.944444444444444
      },
      "home": {
        "id": 701542,
        "name": "Will Warren",
        "hand": "R",
        "era": 4.03,
        "whip": 1.36,
        "ip": 98.33333333333333,
        "so": 96,
        "bb": 33,
        "hr": 14,
        "gs": 19,
        "gp": 19,
        "w": 7,
        "l": 4,
        "bf": 429,
        "go": 97,
        "ao": 97,
        "h": 101,
        "ab": 385,
        "sf": 5,
        "starterIp": 98.33333333333333,
        "starterGames": 19,
        "score": 63,
        "grade": "Average",
        "note": null,
        "k9": 8.786440677966102,
        "bb9": 3.0203389830508476,
        "kbbPct": 0.14685314685314685,
        "gbPct": 0.5,
        "babip": 0.3107142857142857,
        "hr9": 1.2813559322033898,
        "ipStart": 5.175438596491228
      },
      "gap": 11,
      "strength": "Moderate",
      "edge_team": "New York Yankees"
    },
    "823760": {
      "game_pk": 823760,
      "game": "New York Mets @ Milwaukee Brewers",
      "away_team": "New York Mets",
      "home_team": "Milwaukee Brewers",
      "away": {
        "id": 804267,
        "name": "Zac Thornton",
        "hand": "L",
        "era": 2.6,
        "whip": 0.92,
        "ip": 17.333333333333332,
        "so": 15,
        "bb": 5,
        "hr": 1,
        "gs": 3,
        "gp": 3,
        "w": 0,
        "l": 1,
        "bf": 67,
        "go": 17,
        "ao": 19,
        "h": 11,
        "ab": 61,
        "sf": 0,
        "starterIp": 17.333333333333332,
        "starterGames": 3,
        "score": 76,
        "grade": "Strong",
        "note": "limited innings; treat score with caution",
        "k9": 7.788461538461538,
        "bb9": 2.5961538461538463,
        "kbbPct": 0.14925373134328357,
        "gbPct": 0.4722222222222222,
        "babip": 0.2222222222222222,
        "hr9": 0.5192307692307693,
        "ipStart": 5.777777777777778
      },
      "home": {
        "id": 687075,
        "name": "Brandon Sproat",
        "hand": "R",
        "era": 5.16,
        "whip": 1.37,
        "ip": 82,
        "so": 87,
        "bb": 39,
        "hr": 15,
        "gs": 16,
        "gp": 18,
        "w": 3,
        "l": 4,
        "bf": 352,
        "go": 71,
        "ao": 73,
        "h": 73,
        "ab": 302,
        "sf": 0,
        "starterIp": 74.66666666666666,
        "starterGames": 16,
        "score": 53,
        "grade": "Below avg",
        "note": null,
        "k9": 9.548780487804878,
        "bb9": 4.280487804878049,
        "kbbPct": 0.13636363636363635,
        "gbPct": 0.4930555555555556,
        "babip": 0.29,
        "hr9": 1.646341463414634,
        "ipStart": 4.666666666666666
      },
      "gap": 23,
      "strength": "Strong",
      "edge_team": "New York Mets"
    },
    "824005": {
      "game_pk": 824005,
      "game": "St. Louis Cardinals @ Los Angeles Angels",
      "away_team": "St. Louis Cardinals",
      "home_team": "Los Angeles Angels",
      "away": {
        "id": 669461,
        "name": "Matthew Liberatore",
        "hand": "L",
        "era": 5,
        "whip": 1.48,
        "ip": 93.66666666666667,
        "so": 88,
        "bb": 36,
        "hr": 17,
        "gs": 19,
        "gp": 19,
        "w": 5,
        "l": 6,
        "bf": 412,
        "go": 70,
        "ao": 111,
        "h": 103,
        "ab": 365,
        "sf": 6,
        "starterIp": 93.66666666666667,
        "starterGames": 19,
        "score": 53,
        "grade": "Below avg",
        "note": null,
        "k9": 8.455516014234876,
        "bb9": 3.4590747330960854,
        "kbbPct": 0.1262135922330097,
        "gbPct": 0.3867403314917127,
        "babip": 0.3233082706766917,
        "hr9": 1.6334519572953736,
        "ipStart": 4.929824561403509
      },
      "home": {
        "id": 700712,
        "name": "Walbert Ureña",
        "hand": "R",
        "era": 2.88,
        "whip": 1.32,
        "ip": 81.33333333333333,
        "so": 78,
        "bb": 46,
        "hr": 5,
        "gs": 15,
        "gp": 17,
        "w": 5,
        "l": 7,
        "bf": 354,
        "go": 93,
        "ao": 69,
        "h": 61,
        "ab": 299,
        "sf": 2,
        "starterIp": 79.66666666666666,
        "starterGames": 15,
        "score": 67,
        "grade": "Above avg",
        "note": null,
        "k9": 8.631147540983607,
        "bb9": 5.09016393442623,
        "kbbPct": 0.0903954802259887,
        "gbPct": 0.5740740740740741,
        "babip": 0.25688073394495414,
        "hr9": 0.5532786885245902,
        "ipStart": 5.311111111111111
      },
      "gap": 14,
      "strength": "Strong",
      "edge_team": "Los Angeles Angels"
    },
    "824085": {
      "game_pk": 824085,
      "game": "San Francisco Giants @ Kansas City Royals",
      "away_team": "San Francisco Giants",
      "home_team": "Kansas City Royals",
      "away": {
        "id": 641816,
        "name": "Tyler Mahle",
        "hand": "R",
        "era": 5.31,
        "whip": 1.46,
        "ip": 78,
        "so": 73,
        "bb": 32,
        "hr": 12,
        "gs": 15,
        "gp": 15,
        "w": 2,
        "l": 8,
        "bf": 337,
        "go": 75,
        "ao": 75,
        "h": 82,
        "ab": 299,
        "sf": 4,
        "starterIp": 78,
        "starterGames": 15,
        "score": 50,
        "grade": "Below avg",
        "note": null,
        "k9": 8.423076923076923,
        "bb9": 3.692307692307692,
        "kbbPct": 0.12166172106824925,
        "gbPct": 0.5,
        "babip": 0.3211009174311927,
        "hr9": 1.3846153846153846,
        "ipStart": 5.2
      },
      "home": {
        "id": 679883,
        "name": "Luinder Avila",
        "hand": "R",
        "era": 5.08,
        "whip": 1.62,
        "ip": 56.666666666666664,
        "so": 50,
        "bb": 34,
        "hr": 6,
        "gs": 9,
        "gp": 18,
        "w": 4,
        "l": 3,
        "bf": 248,
        "go": 59,
        "ao": 46,
        "h": 58,
        "ab": 210,
        "sf": 2,
        "starterIp": 38.33333333333333,
        "starterGames": 9,
        "score": 44,
        "grade": "Weak",
        "note": null,
        "k9": 7.941176470588236,
        "bb9": 5.3999999999999995,
        "kbbPct": 0.06451612903225806,
        "gbPct": 0.5619047619047619,
        "babip": 0.3333333333333333,
        "hr9": 0.9529411764705882,
        "ipStart": 4.259259259259259
      },
      "gap": 6,
      "strength": "Slight",
      "edge_team": "San Francisco Giants"
    },
    "824165": {
      "game_pk": 824165,
      "game": "Miami Marlins @ Houston Astros",
      "away_team": "Miami Marlins",
      "home_team": "Houston Astros",
      "away": {
        "id": 663969,
        "name": "Tyler Phillips",
        "hand": "R",
        "era": 3.48,
        "whip": 1.39,
        "ip": 75,
        "so": 56,
        "bb": 35,
        "hr": 8,
        "gs": 9,
        "gp": 25,
        "w": 2,
        "l": 4,
        "bf": 324,
        "go": 88,
        "ao": 73,
        "h": 69,
        "ab": 285,
        "sf": 0,
        "starterIp": 40.33333333333333,
        "starterGames": 9,
        "score": 61,
        "grade": "Average",
        "note": null,
        "k9": 6.720000000000001,
        "bb9": 4.2,
        "kbbPct": 0.06481481481481481,
        "gbPct": 0.546583850931677,
        "babip": 0.27601809954751133,
        "hr9": 0.9600000000000001,
        "ipStart": 4.481481481481481
      },
      "home": {
        "id": 837227,
        "name": "Tatsuya Imai",
        "hand": "R",
        "era": 6.06,
        "whip": 1.5,
        "ip": 52,
        "so": 63,
        "bb": 33,
        "hr": 9,
        "gs": 13,
        "gp": 13,
        "w": 5,
        "l": 4,
        "bf": 233,
        "go": 46,
        "ao": 42,
        "h": 45,
        "ab": 194,
        "sf": 1,
        "starterIp": 52,
        "starterGames": 13,
        "score": 43,
        "grade": "Weak",
        "note": null,
        "k9": 10.903846153846153,
        "bb9": 5.711538461538462,
        "kbbPct": 0.12875536480686695,
        "gbPct": 0.5227272727272727,
        "babip": 0.2926829268292683,
        "hr9": 1.5576923076923077,
        "ipStart": 4
      },
      "gap": 18,
      "strength": "Strong",
      "edge_team": "Miami Marlins"
    },
    "824329": {
      "game_pk": 824329,
      "game": "Washington Nationals @ Colorado Rockies",
      "away_team": "Washington Nationals",
      "home_team": "Colorado Rockies",
      "away": {
        "id": 687223,
        "name": "Carson Palmquist",
        "hand": "L",
        "era": 6.52,
        "whip": 1.45,
        "ip": 9.666666666666666,
        "so": 12,
        "bb": 2,
        "hr": 1,
        "gs": 3,
        "gp": 6,
        "w": 0,
        "l": 1,
        "bf": 43,
        "go": 5,
        "ao": 10,
        "h": 12,
        "ab": 39,
        "sf": 0,
        "starterIp": 7.333333333333334,
        "starterGames": 3,
        "score": 43,
        "grade": "Weak",
        "note": "limited innings; treat score with caution",
        "k9": 11.172413793103448,
        "bb9": 1.8620689655172415,
        "kbbPct": 0.23255813953488372,
        "gbPct": 0.3333333333333333,
        "babip": 0.4230769230769231,
        "hr9": 0.9310344827586208,
        "ipStart": 2.4444444444444446
      },
      "home": {
        "id": 547179,
        "name": "Michael Lorenzen",
        "hand": "R",
        "era": 6.22,
        "whip": 1.77,
        "ip": 97,
        "so": 73,
        "bb": 38,
        "hr": 14,
        "gs": 20,
        "gp": 21,
        "w": 3,
        "l": 9,
        "bf": 463,
        "go": 111,
        "ao": 102,
        "h": 134,
        "ab": 413,
        "sf": 6,
        "starterIp": 95.99999999999999,
        "starterGames": 20,
        "score": 37,
        "grade": "Weak",
        "note": null,
        "k9": 6.77319587628866,
        "bb9": 3.5257731958762886,
        "kbbPct": 0.0755939524838013,
        "gbPct": 0.5211267605633803,
        "babip": 0.3614457831325301,
        "hr9": 1.2989690721649483,
        "ipStart": 4.799999999999999
      },
      "gap": 6,
      "strength": "Slight",
      "edge_team": "Washington Nationals"
    },
    "824409": {
      "game_pk": 824409,
      "game": "Minnesota Twins @ Cleveland Guardians",
      "away_team": "Minnesota Twins",
      "home_team": "Cleveland Guardians",
      "away": {
        "id": 696070,
        "name": "Kendry Rojas",
        "hand": "L",
        "era": 2.79,
        "whip": 1.6,
        "ip": 19.333333333333332,
        "so": 22,
        "bb": 16,
        "hr": 1,
        "gs": 2,
        "gp": 8,
        "w": 1,
        "l": 1,
        "bf": 86,
        "go": 14,
        "ao": 18,
        "h": 15,
        "ab": 68,
        "sf": 0,
        "starterIp": 6,
        "starterGames": 2,
        "score": 57,
        "grade": "Average",
        "note": "limited innings; treat score with caution",
        "k9": 10.241379310344827,
        "bb9": 7.448275862068966,
        "kbbPct": 0.06976744186046512,
        "gbPct": 0.4375,
        "babip": 0.3111111111111111,
        "hr9": 0.4655172413793104,
        "ipStart": 3
      },
      "home": {
        "id": 800048,
        "name": "Parker Messick",
        "hand": "L",
        "era": 2.73,
        "whip": 1.07,
        "ip": 112,
        "so": 110,
        "bb": 36,
        "hr": 10,
        "gs": 19,
        "gp": 19,
        "w": 8,
        "l": 5,
        "bf": 445,
        "go": 106,
        "ao": 108,
        "h": 84,
        "ab": 402,
        "sf": 3,
        "starterIp": 112,
        "starterGames": 19,
        "score": 78,
        "grade": "Strong",
        "note": null,
        "k9": 8.839285714285714,
        "bb9": 2.8928571428571432,
        "kbbPct": 0.1662921348314607,
        "gbPct": 0.4953271028037383,
        "babip": 0.2596491228070175,
        "hr9": 0.8035714285714286,
        "ipStart": 5.894736842105263
      },
      "gap": 21,
      "strength": "Strong",
      "edge_team": "Cleveland Guardians"
    },
    "824652": {
      "game_pk": 824652,
      "game": "Detroit Tigers @ Chicago Cubs",
      "away_team": "Detroit Tigers",
      "home_team": "Chicago Cubs",
      "away": {
        "id": 664285,
        "name": "Framber Valdez",
        "hand": "L",
        "era": 4.1,
        "whip": 1.32,
        "ip": 107.66666666666667,
        "so": 87,
        "bb": 36,
        "hr": 11,
        "gs": 19,
        "gp": 19,
        "w": 5,
        "l": 6,
        "bf": 469,
        "go": 131,
        "ao": 99,
        "h": 106,
        "ab": 420,
        "sf": 3,
        "starterIp": 107.66666666666667,
        "starterGames": 19,
        "score": 62,
        "grade": "Average",
        "note": null,
        "k9": 7.272445820433436,
        "bb9": 3.009287925696594,
        "kbbPct": 0.10874200426439233,
        "gbPct": 0.5695652173913044,
        "babip": 0.2923076923076923,
        "hr9": 0.9195046439628483,
        "ipStart": 5.666666666666667
      },
      "home": {
        "id": 656849,
        "name": "David Peterson",
        "hand": "L",
        "era": 6.45,
        "whip": 1.64,
        "ip": 82.33333333333333,
        "so": 70,
        "bb": 37,
        "hr": 9,
        "gs": 11,
        "gp": 19,
        "w": 4,
        "l": 7,
        "bf": 382,
        "go": 99,
        "ao": 75,
        "h": 98,
        "ab": 336,
        "sf": 5,
        "starterIp": 51.66666666666666,
        "starterGames": 11,
        "score": 38,
        "grade": "Weak",
        "note": null,
        "k9": 7.651821862348179,
        "bb9": 4.044534412955466,
        "kbbPct": 0.08638743455497382,
        "gbPct": 0.5689655172413793,
        "babip": 0.33969465648854963,
        "hr9": 0.9838056680161944,
        "ipStart": 4.696969696969696
      },
      "gap": 24,
      "strength": "Strong",
      "edge_team": "Detroit Tigers"
    },
    "824735": {
      "game_pk": 824735,
      "game": "Baltimore Orioles @ Boston Red Sox",
      "away_team": "Baltimore Orioles",
      "home_team": "Boston Red Sox",
      "away": {
        "id": 680694,
        "name": "Kyle Bradish",
        "hand": "R",
        "era": 3.61,
        "whip": 1.35,
        "ip": 107.33333333333333,
        "so": 106,
        "bb": 50,
        "hr": 12,
        "gs": 19,
        "gp": 19,
        "w": 6,
        "l": 9,
        "bf": 454,
        "go": 118,
        "ao": 84,
        "h": 95,
        "ab": 401,
        "sf": 2,
        "starterIp": 107.33333333333333,
        "starterGames": 19,
        "score": 64,
        "grade": "Average",
        "note": null,
        "k9": 8.888198757763975,
        "bb9": 4.192546583850932,
        "kbbPct": 0.12334801762114538,
        "gbPct": 0.5841584158415841,
        "babip": 0.2912280701754386,
        "hr9": 1.0062111801242237,
        "ipStart": 5.649122807017544
      },
      "home": {
        "id": 700842,
        "name": "Eduardo Rivera",
        "hand": "L",
        "era": 2.89,
        "whip": 0.96,
        "ip": 9.333333333333334,
        "so": 9,
        "bb": 4,
        "hr": 1,
        "gs": 2,
        "gp": 3,
        "w": 0,
        "l": 0,
        "bf": 36,
        "go": 10,
        "ao": 8,
        "h": 5,
        "ab": 32,
        "sf": 0,
        "starterIp": 6,
        "starterGames": 2,
        "score": 73,
        "grade": "Above avg",
        "note": "limited innings; treat score with caution",
        "k9": 8.678571428571427,
        "bb9": 3.8571428571428568,
        "kbbPct": 0.1388888888888889,
        "gbPct": 0.5555555555555556,
        "babip": 0.18181818181818182,
        "hr9": 0.9642857142857142,
        "ipStart": 3
      },
      "gap": 9,
      "strength": "Moderate",
      "edge_team": "Boston Red Sox"
    },
    "824895": {
      "game_pk": 824895,
      "game": "San Diego Padres @ Atlanta Braves",
      "away_team": "San Diego Padres",
      "home_team": "Atlanta Braves",
      "away": {
        "id": 621111,
        "name": "Walker Buehler",
        "hand": "R",
        "era": 5.36,
        "whip": 1.44,
        "ip": 89,
        "so": 81,
        "bb": 35,
        "hr": 12,
        "gs": 19,
        "gp": 19,
        "w": 5,
        "l": 5,
        "bf": 388,
        "go": 91,
        "ao": 84,
        "h": 93,
        "ab": 349,
        "sf": 0,
        "starterIp": 89,
        "starterGames": 19,
        "score": 51,
        "grade": "Below avg",
        "note": null,
        "k9": 8.191011235955056,
        "bb9": 3.539325842696629,
        "kbbPct": 0.11855670103092783,
        "gbPct": 0.52,
        "babip": 0.31640625,
        "hr9": 1.2134831460674156,
        "ipStart": 4.684210526315789
      },
      "home": {
        "id": 625643,
        "name": "Reynaldo López",
        "hand": "R",
        "era": 3.5,
        "whip": 1.26,
        "ip": 61.666666666666664,
        "so": 54,
        "bb": 25,
        "hr": 8,
        "gs": 9,
        "gp": 22,
        "w": 4,
        "l": 2,
        "bf": 260,
        "go": 57,
        "ao": 69,
        "h": 53,
        "ab": 232,
        "sf": 1,
        "starterIp": 39.66666666666667,
        "starterGames": 9,
        "score": 65,
        "grade": "Above avg",
        "note": null,
        "k9": 7.881081081081081,
        "bb9": 3.6486486486486487,
        "kbbPct": 0.11153846153846154,
        "gbPct": 0.4523809523809524,
        "babip": 0.2631578947368421,
        "hr9": 1.1675675675675676,
        "ipStart": 4.407407407407408
      },
      "gap": 14,
      "strength": "Strong",
      "edge_team": "Atlanta Braves"
    },
    "825056": {
      "game_pk": 825056,
      "game": "Athletics @ Arizona Diamondbacks",
      "away_team": "Athletics",
      "home_team": "Arizona Diamondbacks",
      "away": {
        "id": 678022,
        "name": "Jack Perkins",
        "hand": "R",
        "era": 6.87,
        "whip": 1.44,
        "ip": 57.666666666666664,
        "so": 72,
        "bb": 23,
        "hr": 10,
        "gs": 6,
        "gp": 24,
        "w": 2,
        "l": 5,
        "bf": 264,
        "go": 40,
        "ao": 62,
        "h": 60,
        "ab": 231,
        "sf": 3,
        "starterIp": 26.666666666666668,
        "starterGames": 6,
        "score": 42,
        "grade": "Weak",
        "note": null,
        "k9": 11.23699421965318,
        "bb9": 3.5895953757225434,
        "kbbPct": 0.1856060606060606,
        "gbPct": 0.39215686274509803,
        "babip": 0.32894736842105265,
        "hr9": 1.560693641618497,
        "ipStart": 4.444444444444445
      },
      "home": {
        "id": 684442,
        "name": "Kohl Drake",
        "hand": "L",
        "era": null,
        "whip": null,
        "ip": 0,
        "so": 0,
        "bb": 0,
        "hr": 0,
        "gs": 0,
        "gp": null,
        "w": 0,
        "l": 0,
        "bf": 0,
        "go": 0,
        "ao": 0,
        "h": 0,
        "ab": 0,
        "sf": 0,
        "starterIp": null,
        "starterGames": null,
        "score": 50,
        "grade": "Unknown",
        "note": "season stats unavailable; neutral score used",
        "k9": null,
        "bb9": null,
        "kbbPct": null,
        "gbPct": null,
        "babip": null,
        "hr9": null,
        "ipStart": null
      },
      "gap": 8,
      "strength": "Moderate",
      "edge_team": "Arizona Diamondbacks"
    }
  }
}
